{
  "maintainer": [
    {
      "name": "Saikiran",
      "socials": {
        "telegram": "Saikiran008",
        "github": "Saikiran2001",
        "xda": "saikiran001.8222620"
      }
    }
  ],
  "active": true,
  "android_version": 13,
  "available_versions": [13],
  "release": "monthly",
  "device_display_name": "Xiaomi Mi Pad 5",
  "device_display_codename": "nabu",
  "device_telegram_group": "AwakenOSLisa",
  "public_download": "https://www.pling.com/p/1422701/",
  "response": [
    {
      "datetime": 1696475277,
      "size": 1915147400,
      "filehash": "1a4bacce583238c1c04c398edb389d0a",
      "filename": "awaken-3.10-triton_void-nabu-official-0310-20231005.zip",
      "id": "f21117af82821ad501bd477e6515fa96ed529617790fee7ae44309300b11d4a3",
      "romtype": "official",
      "version": "3.10",
      "url": "https://sourceforge.net/projects/project-awaken/files/nabu/3.10/awaken-3.10-triton_void-nabu-official-0310-20231005.zip/download"
    }
  ]
}
